setup.py
shuwen_gateway_sign_sdk/__init__.py
shuwen_gateway_sign_sdk/auth_util_v1.py
shuwen_gateway_sign_sdk/auth_util_v2.py
shuwen_gateway_sign_sdk/pkg_info.py
shuwen_gateway_sign_sdk.egg-info/PKG-INFO
shuwen_gateway_sign_sdk.egg-info/SOURCES.txt
shuwen_gateway_sign_sdk.egg-info/dependency_links.txt
shuwen_gateway_sign_sdk.egg-info/top_level.txt